yumo/__about__.py
yumo/__init__.py
yumo/__main__.py
yumo/app.py
yumo/base_structure.py
yumo/constants.py
yumo/context.py
yumo/geometry_utils.py
yumo/mesh.py
yumo/point_cloud.py
yumo/slices.py
yumo/ui.py
yumo/utils.py
yumo/assets/colormaps/RdBu_colormap.png
yumo/assets/materials/0.00_clay_1.00_flat_b.hdr
yumo/assets/materials/0.00_clay_1.00_flat_g.hdr
yumo/assets/materials/0.00_clay_1.00_flat_k.hdr
yumo/assets/materials/0.00_clay_1.00_flat_r.hdr
yumo/assets/materials/0.10_clay_0.90_flat_b.hdr
yumo/assets/materials/0.10_clay_0.90_flat_g.hdr
yumo/assets/materials/0.10_clay_0.90_flat_k.hdr
yumo/assets/materials/0.10_clay_0.90_flat_r.hdr
yumo/assets/materials/0.20_clay_0.80_flat_b.hdr
yumo/assets/materials/0.20_clay_0.80_flat_g.hdr
yumo/assets/materials/0.20_clay_0.80_flat_k.hdr
yumo/assets/materials/0.20_clay_0.80_flat_r.hdr
yumo/assets/materials/0.30_clay_0.70_flat_b.hdr
yumo/assets/materials/0.30_clay_0.70_flat_g.hdr
yumo/assets/materials/0.30_clay_0.70_flat_k.hdr
yumo/assets/materials/0.30_clay_0.70_flat_r.hdr
yumo/assets/materials/0.40_clay_0.60_flat_b.hdr
yumo/assets/materials/0.40_clay_0.60_flat_g.hdr
yumo/assets/materials/0.40_clay_0.60_flat_k.hdr
yumo/assets/materials/0.40_clay_0.60_flat_r.hdr
yumo/assets/materials/0.50_clay_0.50_flat_b.hdr
yumo/assets/materials/0.50_clay_0.50_flat_g.hdr
yumo/assets/materials/0.50_clay_0.50_flat_k.hdr
yumo/assets/materials/0.50_clay_0.50_flat_r.hdr
yumo/assets/materials/0.60_clay_0.40_flat_b.hdr
yumo/assets/materials/0.60_clay_0.40_flat_g.hdr
yumo/assets/materials/0.60_clay_0.40_flat_k.hdr
yumo/assets/materials/0.60_clay_0.40_flat_r.hdr
yumo/assets/materials/0.70_clay_0.30_flat_b.hdr
yumo/assets/materials/0.70_clay_0.30_flat_g.hdr
yumo/assets/materials/0.70_clay_0.30_flat_k.hdr
yumo/assets/materials/0.70_clay_0.30_flat_r.hdr
yumo/assets/materials/0.80_clay_0.20_flat_b.hdr
yumo/assets/materials/0.80_clay_0.20_flat_g.hdr
yumo/assets/materials/0.80_clay_0.20_flat_k.hdr
yumo/assets/materials/0.80_clay_0.20_flat_r.hdr
yumo-0.1.3.dist-info/licenses/LICENSE
yumo-0.1.3.dist-info/METADATA
yumo-0.1.3.dist-info/WHEEL
yumo-0.1.3.dist-info/entry_points.txt
yumo-0.1.3.dist-info/top_level.txt
yumo-0.1.3.dist-info/RECORD
