Metadata-Version: 2.4
Name: yumo
Version: 0.1.3
Summary: Scalar field visualization using Polyscope.
Author: Chaofan Luo
Project-URL: Homepage, https://luocfprime.github.io/yumo/
Project-URL: Repository, https://github.com/luocfprime/yumo
Project-URL: Documentation, https://luocfprime.github.io/yumo/
Keywords: python
Classifier: Intended Audience :: Developers
Classifier: Programming Language :: Python
Classifier: Programming Language :: Python :: 3
Classifier: Programming Language :: Python :: 3.10
Classifier: Programming Language :: Python :: 3.11
Classifier: Programming Language :: Python :: 3.12
Classifier: Topic :: Software Development :: Libraries :: Python Modules
Requires-Python: <4.0,>=3.10
License-File: LICENSE
Requires-Dist: einx>=0.3.0
Requires-Dist: matplotlib>=3.9.4
Requires-Dist: natsort>=8.4.0
Requires-Dist: numpy>=1.26.4
Requires-Dist: opencv-python>=4.11.0.86
Requires-Dist: polyscope>=2.5.0
Requires-Dist: rtree>=1.4.1
Requires-Dist: scipy>=1.15.3
Requires-Dist: tqdm>=4.67.1
Requires-Dist: trimesh>=4.8.1
Requires-Dist: typer>=0.17.4
Requires-Dist: xatlas>=0.0.11
Provides-Extra: dev
Requires-Dist: pytest>=7.2.0; extra == "dev"
Requires-Dist: pytest-cov>=4.0.0; extra == "dev"
Requires-Dist: pre-commit>=2.20.0; extra == "dev"
Requires-Dist: tox-uv>=1.11.3; extra == "dev"
Requires-Dist: mypy>=0.991; extra == "dev"
Requires-Dist: ruff>=0.9.2; extra == "dev"
Requires-Dist: mkdocs>=1.4.2; extra == "dev"
Requires-Dist: mkdocs-material>=8.5.10; extra == "dev"
Requires-Dist: mkdocstrings[python]>=0.26.1; extra == "dev"
Requires-Dist: mkdocs-static-i18n[material]>=1.3.0; extra == "dev"
Requires-Dist: mkdocs-macros-plugin>=1.3.9; extra == "dev"
Requires-Dist: tomlkit>=0.13.3; extra == "dev"
Dynamic: license-file
